{
  "persons": [
    {
      "name": "Arto Hellas",
      "number": "040-123456",
      "id": 1
    },
    {
      "name": "Ada Lovelace",
      "number": "39-44-5323523",
      "id": 2
    },
    {
      "name": "Dan Abramov",
      "number": "12-43-234345",
      "id": 3
    },
    {
      "name": "Mary Poppendieck",
      "number": "39-23-6423122",
      "id": 4
    },
    {
      "name": "asdfads",
      "number": "12",
      "id": 5
    },
    {
      "name": "ass",
      "number": "345",
      "id": 6
    },
    {
      "name": "asses",
      "number": "345345",
      "id": 7
    },
    {
      "name": "asdfasdf",
      "number": "234324234",
      "id": 8
    },
    {
      "name": "vcxbv",
      "number": "1",
      "id": 10
    },
    {
      "name": "Arturo",
      "number": "34234",
      "id": 11
    },
    {
      "name": "pepe",
      "number": "123",
      "id": 12
    },
    {
      "name": "pepex",
      "number": "1234",
      "id": 13
    },
    {
      "name": "12",
      "number": "1",
      "id": 14
    }
  ]
}